rummage/__init__.py
rummage/__main__.py
rummage/lib/__init__.py
rummage/lib/__meta__.py
rummage/lib/__version__.py
rummage/lib/safe_import.py
rummage/lib/gui/__init__.py
rummage/lib/gui/about_dialog.py
rummage/lib/gui/checksum_dialog.py
rummage/lib/gui/delete_dialog.py
rummage/lib/gui/edit_search_chain_dialog.py
rummage/lib/gui/editor_dialog.py
rummage/lib/gui/error_text_dialog.py
rummage/lib/gui/export_settings_dialog.py
rummage/lib/gui/generic_dialogs.py
rummage/lib/gui/gui.py
rummage/lib/gui/import_settings_dialog.py
rummage/lib/gui/load_search_dialog.py
rummage/lib/gui/messages.py
rummage/lib/gui/overwrite_dialog.py
rummage/lib/gui/regex_test_dialog.py
rummage/lib/gui/rummage_dialog.py
rummage/lib/gui/save_search_dialog.py
rummage/lib/gui/search_chain_dialog.py
rummage/lib/gui/search_error_dialog.py
rummage/lib/gui/settings_dialog.py
rummage/lib/gui/support_info_dialog.py
rummage/lib/gui/actions/__init__.py
rummage/lib/gui/actions/export_csv.py
rummage/lib/gui/actions/export_html.py
rummage/lib/gui/actions/fileops.py
rummage/lib/gui/actions/updates.py
rummage/lib/gui/actions/checksum/__init__.py
rummage/lib/gui/actions/checksum/sum_hashes.py
rummage/lib/gui/actions/checksum/tiger.py
rummage/lib/gui/actions/checksum/whirlpool.py
rummage/lib/gui/app/__init__.py
rummage/lib/gui/app/custom_app.py
rummage/lib/gui/app/platform_window_focus.py
rummage/lib/gui/app/rummage_app.py
rummage/lib/gui/controls/__init__.py
rummage/lib/gui/controls/autocomplete_combo.py
rummage/lib/gui/controls/custom_statusbar.py
rummage/lib/gui/controls/date_picker.py
rummage/lib/gui/controls/dynamic_lists.py
rummage/lib/gui/controls/list_box.py
rummage/lib/gui/controls/load_search_list.py
rummage/lib/gui/controls/pick_button.py
rummage/lib/gui/controls/result_lists.py
rummage/lib/gui/controls/search_chain_list.py
rummage/lib/gui/controls/search_error_list.py
rummage/lib/gui/data/__init__.py
rummage/lib/gui/data/binary.png
rummage-3.5.dist-info/DESCRIPTION.rst
rummage-3.5.dist-info/METADATA
rummage-3.5.dist-info/RECORD
rummage-3.5.dist-info/WHEEL
rummage-3.5.dist-info/entry_points.txt
rummage-3.5.dist-info/metadata.json
rummage-3.5.dist-info/top_level.txt
