Metadata-Version: 2.0
Name: rummage
Version: 3.5
Summary: A GUI search and replace app.
Home-page: https://github.com/facelessuser/Rummage
Author: Isaac Muse
Author-email: Isaac.Muse@gmail.com
License: MIT License
Keywords: grep search find replace gui
Platform: UNKNOWN
Classifier: Development Status :: 5 - Production/Stable
Classifier: Environment :: Console
Classifier: Intended Audience :: Developers
Classifier: License :: OSI Approved :: MIT License
Classifier: Operating System :: OS Independent
Classifier: Programming Language :: Python :: 2
Classifier: Programming Language :: Python :: 2.7
Classifier: Programming Language :: Python :: 3
Classifier: Programming Language :: Python :: 3.4
Classifier: Programming Language :: Python :: 3.5
Classifier: Programming Language :: Python :: 3.6
Classifier: Topic :: Software Development :: Libraries :: Python Modules
Requires-Dist: gntp (>=1.0.2)
Requires-Dist: chardet (>=3.0.4)
Requires-Dist: backrefs (<4.0,>=3.0.3)
Requires-Dist: wxpython (>=4.0.0a3)
Requires-Dist: filelock
Requires-Dist: send2trash
